examples/_solutions/lab4-counter/clk_en.v
// =================================================
//! @brief Clock enable generator (single-cycle pulse)
//! @version 2.0
//! @copyright (c) 2019-2026 Tomas Fryza, MIT license
//!
//! This design generates a single-clock-cycle enable
//! pulse every MAX clock cycles.
//
// Notes:
// - Synchronous design (positive edge of clk)
// - High-active synchronous reset
// - Output pulse width = one clock period
// - MAX must be greater than 0
// =================================================

module clk_en #(
    // #() after a module name introduces a parameter list
    parameter MAX = 4  //! Number of clock cycles between pulses
)(
    input  wire clk,  //! Main clock
    input  wire rst,  //! High-active synchronous reset
    output reg  ce    //! One-clock-cycle enable pulse
);

    // Internal counter
    reg [$clog2(MAX)-1:0] sig_cnt;
    // $clog2(MAX) -- Ceiling of log2(x) returns the minimum
    // number of bits required

    // Clocked, sequential process, triggerd when clk rises
    // from 0 to 1 (positive edge of a signal)
    always @(posedge clk) begin
        if (rst) begin
            ce      <= 1'b0;     // Reset output
            sig_cnt <= 0;        // Reset internal counter
        end
        else if (sig_cnt == MAX-1) begin
            ce      <= 1'b1;     // Generate one-cycle pulse
            sig_cnt <= 0;        // Reset counter
        end
        else begin
            ce      <= 1'b0;     // Clear output
            sig_cnt <= sig_cnt + 1;  // Increment internal counter
        end
    end

endmodule

examples/_solutions/lab4-counter/clk_en_tb.v
// Time unit = 1 ns / Time precision = 1 ps
`timescale 1ns/1ps

// =================================================
// Testbench for clock enable generator
// =================================================

module clk_en_tb ();

    // ---------------------------------------------
    // Testbench internal signals and parameter
    // Must be `reg`, so we can assign values
    // ---------------------------------------------
    parameter MAX = 12;  // Change only this value to modify counting
    reg  clk;
    reg  rst;
    wire ce;

    // ---------------------------------------------
    // Instantiate Device Under Test (DUT)
    // ---------------------------------------------
    // clk_en -- module name
    // #() -- parameter override block
    // .MAX (MAX) -- named parameter mapping
    // dut -- instance name of this module
    // .clk (clk) -- connect/map module port clk to testbench signal clk
    clk_en #(
        .MAX (MAX)
    ) dut (
        .clk (clk),
        .rst (rst),
        .ce  (ce)
    );

    // Clock generation: 10 ns period
    always #5 clk = ~clk;
    // `always` defines a process that runs indefinitely during
    // simulation. This block repeats forever.

    // ---------------------------------------------
    // Stimulus process
    // Applies test vectors to DUT inputs over time
    // ---------------------------------------------
    initial begin
        // Waveform dump for GTKWave
        $dumpfile("counter.vcd");
        $dumpvars(0, clk_en_tb);

        // Use the monitor task to automaticaly display any change
        $monitor("[%3d] clk=%b rst=%b ce=%b  cnt=%d",
            $time, clk, rst, ce,
            clk_en_tb.dut.sig_cnt);  // <--- hierarchical path
        
        // Initialize signals
        clk = 0;
        rst = 1;

        // Hold reset for a few clock cycles
        #20;
        rst = 0;

        // Let it run for several pulses
        #200;

        rst = 1;
        #20;
        rst = 0;
        #200;

        $finish;
    end

endmodule

examples/_solutions/lab4-counter/counter.vcd
$date
	Sun Mar  1 10:20:28 2026
$end
$version
	Icarus Verilog
$end
$timescale
	1ps
$end
$scope module clk_en_tb $end
$var wire 1 ! ce $end
$var parameter 32 " MAX $end
$var reg 1 # clk $end
$var reg 1 $ rst $end
$scope module dut $end
$var wire 1 # clk $end
$var wire 1 $ rst $end
$var parameter 32 % MAX $end
$var reg 1 ! ce $end
$var reg 4 & sig_cnt [3:0] $end
$upscope $end
$upscope $end
$enddefinitions $end
$comment Show the parameter values. $end
$dumpall
b1100 %
b1100 "
$end
#0
$dumpvars
bx &
1$
0#
x!
$end
#5000
b0 &
0!
1#
#10000
0#
#15000
1#
#20000
0#
0$
#25000
b1 &
1#
#30000
0#
#35000
b10 &
1#
#40000
0#
#45000
b11 &
1#
#50000
0#
#55000
b100 &
1#
#60000
0#
#65000
b101 &
1#
#70000
0#
#75000
b110 &
1#
#80000
0#
#85000
b111 &
1#
#90000
0#
#95000
b1000 &
1#
#100000
0#
#105000
b1001 &
1#
#110000
0#
#115000
b1010 &
1#
#120000
0#
#125000
b1011 &
1#
#130000
0#
#135000
b0 &
1!
1#
#140000
0#
#145000
b1 &
0!
1#
#150000
0#
#155000
b10 &
1#
#160000
0#
#165000
b11 &
1#
#170000
0#
#175000
b100 &
1#
#180000
0#
#185000
b101 &
1#
#190000
0#
#195000
b110 &
1#
#200000
0#
#205000
b111 &
1#
#210000
0#
#215000
b1000 &
1#
#220000
0#
1$
#225000
b0 &
1#
#230000
0#
#235000
1#
#240000
0#
0$
#245000
b1 &
1#
#250000
0#
#255000
b10 &
1#
#260000
0#
#265000
b11 &
1#
#270000
0#
#275000
b100 &
1#
#280000
0#
#285000
b101 &
1#
#290000
0#
#295000
b110 &
1#
#300000
0#
#305000
b111 &
1#
#310000
0#
#315000
b1000 &
1#
#320000
0#
#325000
b1001 &
1#
#330000
0#
#335000
b1010 &
1#
#340000
0#
#345000
b1011 &
1#
#350000
0#
#355000
b0 &
1!
1#
#360000
0#
#365000
b1 &
0!
1#
#370000
0#
#375000
b10 &
1#
#380000
0#
#385000
b11 &
1#
#390000
0#
#395000
b100 &
1#
#400000
0#
#405000
b101 &
1#
#410000
0#
#415000
b110 &
1#
#420000
0#
#425000
b111 &
1#
#430000
0#
#435000
b1000 &
1#
